{"pr_number": 749, "pr_title": "feat(engine): introduce READ_VARIABLE permission for historic tasks", "pr_author": "tasso94", "pr_createdAt": "2020-03-23T15:25:09Z", "pr_url": "https://github.com/camunda/camunda-bpm-platform/pull/749", "timeline": [{"oid": "257d64886de8ecbc9a7909a4fd71fce49a38b16b", "url": "https://github.com/camunda/camunda-bpm-platform/commit/257d64886de8ecbc9a7909a4fd71fce49a38b16b", "message": "feat(engine): introduce READ_VARIABLE permission for historic tasks\n\nrelated to CAM-11626", "committedDate": "2020-03-24T13:24:19Z", "type": "forcePushed"}, {"oid": "e1f0b9cc7bb3ed0251c7568e3dd33cb48f965776", "url": "https://github.com/camunda/camunda-bpm-platform/commit/e1f0b9cc7bb3ed0251c7568e3dd33cb48f965776", "message": "feat(engine): introduce READ_VARIABLE permission for historic tasks\n\nrelated to CAM-11626", "committedDate": "2020-03-24T14:18:54Z", "type": "forcePushed"}, {"id": "MDI0OlB1bGxSZXF1ZXN0UmV2aWV3Q29tbWVudDM5OTI2NTQzNA==", "url": "https://github.com/camunda/camunda-bpm-platform/pull/749#discussion_r399265434", "body": "note to myself, double check the value ", "bodyText": "note to myself, double check the value", "bodyHTML": "<p dir=\"auto\">note to myself, double check the value</p>", "author": "yanavasileva", "createdAt": "2020-03-27T13:31:41Z", "path": "engine/src/main/java/org/camunda/bpm/engine/authorization/HistoricTaskPermissions.java", "diffHunk": "@@ -40,7 +40,10 @@\n   ALL(\"ALL\", Integer.MAX_VALUE),\n \n   /** Indicates that READ interactions are permitted. */\n-  READ(\"READ\", 2);\n+  READ(\"READ\", 2),\n+\n+  /** Indicates that READ_VARIABLE interactions are permitted. */\n+  READ_VARIABLE(\"READ_VARIABLE\", 4);", "originalCommit": "e1f0b9cc7bb3ed0251c7568e3dd33cb48f965776", "replyToReviewId": null, "replies": [{"id": "MDI0OlB1bGxSZXF1ZXN0UmV2aWV3Q29tbWVudDQwMDI3MDQyNQ==", "url": "https://github.com/camunda/camunda-bpm-platform/pull/749#discussion_r400270425", "bodyText": "we agreed to put 64 as value for READ_VARIABLE permission to be consistent with TaskPermissions#READ_VARIABLE", "author": "yanavasileva", "createdAt": "2020-03-30T15:11:48Z", "replyToReviewId": "MDI0OlB1bGxSZXF1ZXN0UmV2aWV3Q29tbWVudDM5OTI2NTQzNA=="}, {"id": "MDI0OlB1bGxSZXF1ZXN0UmV2aWV3Q29tbWVudDQwMDI3MTY5OA==", "url": "https://github.com/camunda/camunda-bpm-platform/pull/749#discussion_r400271698", "bodyText": "This file contains bidirectional Unicode text that may be interpreted or compiled differently than what appears below. To review, open the file in an editor that reveals hidden Unicode characters. Learn more about bidirectional Unicode characters\n\n\n  \n\n\n    \n      \n        Suggested change\n        \n          \n    \n\n        \n      \n    \n    \n      \n          \n            \n              READ_VARIABLE(\"READ_VARIABLE\", 4);\n          \n          \n            \n              READ_VARIABLE(\"READ_VARIABLE\", 64);", "author": "yanavasileva", "createdAt": "2020-03-30T15:13:21Z", "replyToReviewId": "MDI0OlB1bGxSZXF1ZXN0UmV2aWV3Q29tbWVudDM5OTI2NTQzNA=="}], "type": "inlineReview"}, {"id": "MDI0OlB1bGxSZXF1ZXN0UmV2aWV3Q29tbWVudDQwMDExOTEzNg==", "url": "https://github.com/camunda/camunda-bpm-platform/pull/749#discussion_r400119136", "body": "could we fix this typo (wasn't me)\r\n```suggestion\r\n   * will be required to fetch variables when the authorizations are enabled.\r\n```", "bodyText": "could we fix this typo (wasn't me)\n  \n    \n      \n        Suggested change\n        \n          \n    \n\n        \n      \n    \n    \n      \n          \n            \n               * will be required to fetch variables when the autorizations are enabled.\n          \n          \n            \n               * will be required to fetch variables when the authorizations are enabled.", "bodyHTML": "<p dir=\"auto\">could we fix this typo (wasn't me)</p>\n  <div class=\"my-2 border rounded-1 js-suggested-changes-blob diff-view js-check-bidi\" id=\"\">\n    <div class=\"f6 p-2 lh-condensed border-bottom d-flex\">\n      <div class=\"flex-auto flex-items-center color-fg-muted\">\n        Suggested change\n        <span class=\"tooltipped tooltipped-multiline tooltipped-s\" aria-label=\"This code change can be committed by users with write permissions.\">\n          <svg aria-hidden=\"true\" height=\"16\" viewBox=\"0 0 16 16\" version=\"1.1\" width=\"16\" data-view-component=\"true\" class=\"octicon octicon-info hide-sm\">\n    <path fill-rule=\"evenodd\" d=\"M8 1.5a6.5 6.5 0 100 13 6.5 6.5 0 000-13zM0 8a8 8 0 1116 0A8 8 0 010 8zm6.5-.25A.75.75 0 017.25 7h1a.75.75 0 01.75.75v2.75h.25a.75.75 0 010 1.5h-2a.75.75 0 010-1.5h.25v-2h-.25a.75.75 0 01-.75-.75zM8 6a1 1 0 100-2 1 1 0 000 2z\"></path>\n</svg>\n        </span>\n      </div>\n    </div>\n    <div itemprop=\"text\" class=\"blob-wrapper data file\" style=\"margin: 0; border: none; overflow-y: visible; overflow-x: auto;\">\n      <table class=\"d-table tab-size mb-0 width-full\" data-paste-markdown-skip=\"\">\n          <tbody><tr class=\"border-0\">\n            <td class=\"blob-num blob-num-deletion text-right border-0 px-2 py-1 lh-default\" data-line-number=\"\"></td>\n            <td class=\"border-0 px-2 py-1 blob-code-inner blob-code-deletion js-blob-code-deletion blob-code-marker-deletion\">   <span class=\"pl-k\">*</span> will be required to fetch variables when the <span class=\"x x-first x-last\">autorizations</span> are enabled.</td>\n          </tr>\n          <tr class=\"border-0\">\n            <td class=\"blob-num blob-num-addition text-right border-0 px-2 py-1 lh-default\" data-line-number=\"\"></td>\n            <td class=\"border-0 px-2 py-1 blob-code-inner blob-code-addition js-blob-code-addition blob-code-marker-addition\">   <span class=\"pl-k\">*</span> will be required to fetch variables when the <span class=\"x x-first x-last\">authorizations</span> are enabled.</td>\n          </tr>\n      </tbody></table>\n    </div>\n    <div class=\"js-apply-changes\"></div>\n  </div>\n", "author": "yanavasileva", "createdAt": "2020-03-30T11:29:35Z", "path": "engine/src/main/java/org/camunda/bpm/engine/ProcessEngineConfiguration.java", "diffHunk": "@@ -372,6 +372,7 @@\n    * READ_HISTORY_VARIABLE, or\n    * READ_TASK_VARIABLE on Process Definition resource, and\n    * READ_VARIABLE on Task resource\n+   * READ_VARIABLE on Historic Task Instance resource\n    * will be required to fetch variables when the autorizations are enabled.", "originalCommit": "e1f0b9cc7bb3ed0251c7568e3dd33cb48f965776", "replyToReviewId": null, "replies": null, "type": "inlineReview"}, {"id": "MDI0OlB1bGxSZXF1ZXN0UmV2aWV3Q29tbWVudDQwMDE0MTMwMQ==", "url": "https://github.com/camunda/camunda-bpm-platform/pull/749#discussion_r400141301", "body": "```suggestion\r\n    enableHistoricInstancePermissions= processEngineConfiguration.isEnableHistoricInstancePermissions();\r\n    processEngineConfiguration.setEnableHistoricInstancePermissions(true);\r\n\r\n```", "bodyText": "Suggested change\n        \n          \n    \n\n        \n      \n    \n    \n      \n          \n            \n                processEngineConfiguration.setEnableHistoricInstancePermissions(true);\n          \n          \n            \n                enableHistoricInstancePermissions= processEngineConfiguration.isEnableHistoricInstancePermissions();\n          \n          \n            \n                processEngineConfiguration.setEnableHistoricInstancePermissions(true);", "bodyHTML": "  <div class=\"my-2 border rounded-1 js-suggested-changes-blob diff-view js-check-bidi\" id=\"\">\n    <div class=\"f6 p-2 lh-condensed border-bottom d-flex\">\n      <div class=\"flex-auto flex-items-center color-fg-muted\">\n        Suggested change\n        <span class=\"tooltipped tooltipped-multiline tooltipped-s\" aria-label=\"This code change can be committed by users with write permissions.\">\n          <svg aria-hidden=\"true\" height=\"16\" viewBox=\"0 0 16 16\" version=\"1.1\" width=\"16\" data-view-component=\"true\" class=\"octicon octicon-info hide-sm\">\n    <path fill-rule=\"evenodd\" d=\"M8 1.5a6.5 6.5 0 100 13 6.5 6.5 0 000-13zM0 8a8 8 0 1116 0A8 8 0 010 8zm6.5-.25A.75.75 0 017.25 7h1a.75.75 0 01.75.75v2.75h.25a.75.75 0 010 1.5h-2a.75.75 0 010-1.5h.25v-2h-.25a.75.75 0 01-.75-.75zM8 6a1 1 0 100-2 1 1 0 000 2z\"></path>\n</svg>\n        </span>\n      </div>\n    </div>\n    <div itemprop=\"text\" class=\"blob-wrapper data file\" style=\"margin: 0; border: none; overflow-y: visible; overflow-x: auto;\">\n      <table class=\"d-table tab-size mb-0 width-full\" data-paste-markdown-skip=\"\">\n          <tbody><tr class=\"border-0\">\n            <td class=\"blob-num blob-num-deletion text-right border-0 px-2 py-1 lh-default\" data-line-number=\"103\"></td>\n            <td class=\"border-0 px-2 py-1 blob-code-inner blob-code-deletion js-blob-code-deletion blob-code-marker-deletion\">    processEngineConfiguration<span class=\"pl-k\">.</span><span class=\"x x-first\">setEnableHistoricInstancePermissions(</span><span class=\"pl-c1 x x-last\">true</span>);</td>\n          </tr>\n          <tr class=\"border-0\">\n            <td class=\"blob-num blob-num-addition text-right border-0 px-2 py-1 lh-default\" data-line-number=\"103\"></td>\n            <td class=\"border-0 px-2 py-1 blob-code-inner blob-code-addition js-blob-code-addition blob-code-marker-addition\">    <span class=\"x x-first\">enableHistoricInstancePermissions</span><span class=\"pl-k x\">=</span><span class=\"x x-last\"> </span>processEngineConfiguration<span class=\"pl-k\">.</span><span class=\"x x-first x-last\">isEnableHistoricInstancePermissions(</span>);</td>\n          </tr>\n          <tr class=\"border-0\">\n            <td class=\"blob-num blob-num-addition text-right border-0 px-2 py-1 lh-default\" data-line-number=\"104\"></td>\n            <td class=\"border-0 px-2 py-1 blob-code-inner blob-code-addition js-blob-code-addition blob-code-marker-addition\">    processEngineConfiguration<span class=\"pl-k\">.</span>setEnableHistoricInstancePermissions(<span class=\"pl-c1\">true</span>);</td>\n          </tr>\n          <tr class=\"border-0\">\n            <td class=\"blob-num blob-num-addition text-right border-0 px-2 py-1 lh-default\" data-line-number=\"105\"></td>\n            <td class=\"border-0 px-2 py-1 blob-code-inner blob-code-addition js-blob-code-addition blob-code-marker-addition\"></td>\n          </tr>\n      </tbody></table>\n    </div>\n    <div class=\"js-apply-changes\"></div>\n  </div>\n", "author": "yanavasileva", "createdAt": "2020-03-30T12:11:15Z", "path": "engine/src/test/java/org/camunda/bpm/engine/test/api/authorization/TaskReadVariablePermissionAuthorizationTest.java", "diffHunk": "@@ -78,6 +100,7 @@ public void init() {\n \r\n     enforceSpecificVariablePermission = processEngineConfiguration.isEnforceSpecificVariablePermission();\r\n     processEngineConfiguration.setEnforceSpecificVariablePermission(true);\r\n+    processEngineConfiguration.setEnableHistoricInstancePermissions(true);\r", "originalCommit": "e1f0b9cc7bb3ed0251c7568e3dd33cb48f965776", "replyToReviewId": null, "replies": null, "type": "inlineReview"}, {"id": "MDI0OlB1bGxSZXF1ZXN0UmV2aWV3Q29tbWVudDQwMDE0MjI1OA==", "url": "https://github.com/camunda/camunda-bpm-platform/pull/749#discussion_r400142258", "body": "Is it only for debugging purposes, shall we remove it?", "bodyText": "Is it only for debugging purposes, shall we remove it?", "bodyHTML": "<p dir=\"auto\">Is it only for debugging purposes, shall we remove it?</p>", "author": "yanavasileva", "createdAt": "2020-03-30T12:12:58Z", "path": "engine/src/test/java/org/camunda/bpm/engine/test/api/authorization/TaskReadVariablePermissionAuthorizationTest.java", "diffHunk": "@@ -326,22 +350,64 @@ protected void startProcessInstanceByKey(String processKey) {\n \r\n   protected void verifyUserAuthorization(String userId) {\r\n     authRule.disableAuthorization();\r\n-    Authorization userAuthorization = authorizationService.createAuthorizationQuery().userIdIn(userId).singleResult();\r\n-    assertNotNull(userAuthorization);\r\n-    verifyReadVariablePermission(userAuthorization);\r\n+\r\n+    if (AUTHORIZATION_TYP_RUNTIME.equals(authorizationType)) {\r\n+      System.out.println(\"RUNTIME!\");\r", "originalCommit": "e1f0b9cc7bb3ed0251c7568e3dd33cb48f965776", "replyToReviewId": null, "replies": [{"id": "MDI0OlB1bGxSZXF1ZXN0UmV2aWV3Q29tbWVudDQwMDI3MTk2MA==", "url": "https://github.com/camunda/camunda-bpm-platform/pull/749#discussion_r400271960", "bodyText": "This file contains bidirectional Unicode text that may be interpreted or compiled differently than what appears below. To review, open the file in an editor that reveals hidden Unicode characters. Learn more about bidirectional Unicode characters\n\n\n  \n\n\n    \n      \n        Suggested change\n        \n          \n    \n\n        \n      \n    \n    \n      \n          \n            \n                  System.out.println(\"RUNTIME!\");", "author": "yanavasileva", "createdAt": "2020-03-30T15:13:40Z", "replyToReviewId": "MDI0OlB1bGxSZXF1ZXN0UmV2aWV3Q29tbWVudDQwMDE0MjI1OA=="}], "type": "inlineReview"}, {"id": "MDI0OlB1bGxSZXF1ZXN0UmV2aWV3Q29tbWVudDQwMDE0MjQwOQ==", "url": "https://github.com/camunda/camunda-bpm-platform/pull/749#discussion_r400142409", "body": "Is it only for debugging purposes, shall we remove it?", "bodyText": "Is it only for debugging purposes, shall we remove it?", "bodyHTML": "<p dir=\"auto\">Is it only for debugging purposes, shall we remove it?</p>", "author": "yanavasileva", "createdAt": "2020-03-30T12:13:14Z", "path": "engine/src/test/java/org/camunda/bpm/engine/test/api/authorization/TaskReadVariablePermissionAuthorizationTest.java", "diffHunk": "@@ -326,22 +350,64 @@ protected void startProcessInstanceByKey(String processKey) {\n \r\n   protected void verifyUserAuthorization(String userId) {\r\n     authRule.disableAuthorization();\r\n-    Authorization userAuthorization = authorizationService.createAuthorizationQuery().userIdIn(userId).singleResult();\r\n-    assertNotNull(userAuthorization);\r\n-    verifyReadVariablePermission(userAuthorization);\r\n+\r\n+    if (AUTHORIZATION_TYP_RUNTIME.equals(authorizationType)) {\r\n+      System.out.println(\"RUNTIME!\");\r\n+      Authorization runtimeUserAuthorization = authorizationService.createAuthorizationQuery()\r\n+          .resourceType(TASK)\r\n+          .userIdIn(userId)\r\n+          .singleResult();\r\n+\r\n+      assertNotNull(runtimeUserAuthorization);\r\n+      verifyReadVariablePermission(runtimeUserAuthorization, TaskPermissions.READ_VARIABLE);\r\n+\r\n+    } else if (AUTHORIZATION_TYP_HISTORIC.equals(authorizationType)) {\r\n+      System.out.println(\"HISTORY!\");\r", "originalCommit": "e1f0b9cc7bb3ed0251c7568e3dd33cb48f965776", "replyToReviewId": null, "replies": [{"id": "MDI0OlB1bGxSZXF1ZXN0UmV2aWV3Q29tbWVudDQwMDI3MjE2NQ==", "url": "https://github.com/camunda/camunda-bpm-platform/pull/749#discussion_r400272165", "bodyText": "This file contains bidirectional Unicode text that may be interpreted or compiled differently than what appears below. To review, open the file in an editor that reveals hidden Unicode characters. Learn more about bidirectional Unicode characters\n\n\n  \n\n\n    \n      \n        Suggested change\n        \n          \n    \n\n        \n      \n    \n    \n      \n          \n            \n                  System.out.println(\"HISTORY!\");", "author": "yanavasileva", "createdAt": "2020-03-30T15:13:55Z", "replyToReviewId": "MDI0OlB1bGxSZXF1ZXN0UmV2aWV3Q29tbWVudDQwMDE0MjQwOQ=="}], "type": "inlineReview"}, {"oid": "5dc7f2b57ec5563136bce5c2c36e140ab5ca2930", "url": "https://github.com/camunda/camunda-bpm-platform/commit/5dc7f2b57ec5563136bce5c2c36e140ab5ca2930", "message": "feat(engine): introduce READ_VARIABLE permission for historic tasks\n\nrelated to CAM-11626", "committedDate": "2020-03-30T15:40:36Z", "type": "commit"}, {"oid": "5dc7f2b57ec5563136bce5c2c36e140ab5ca2930", "url": "https://github.com/camunda/camunda-bpm-platform/commit/5dc7f2b57ec5563136bce5c2c36e140ab5ca2930", "message": "feat(engine): introduce READ_VARIABLE permission for historic tasks\n\nrelated to CAM-11626", "committedDate": "2020-03-30T15:40:36Z", "type": "forcePushed"}, {"oid": "8b73fd6888affb451d7d93ab879bd488f51c2db5", "url": "https://github.com/camunda/camunda-bpm-platform/commit/8b73fd6888affb451d7d93ab879bd488f51c2db5", "message": "SQUASH ME typo", "committedDate": "2020-03-30T15:42:12Z", "type": "commit"}, {"oid": "cfa258ce1d1483d099474815d77db3a176234f61", "url": "https://github.com/camunda/camunda-bpm-platform/commit/cfa258ce1d1483d099474815d77db3a176234f61", "message": "SQUASH ME remove syso", "committedDate": "2020-03-30T15:42:32Z", "type": "commit"}, {"oid": "365fdedd644f87752d1ad4e7b1d42a6b0997093c", "url": "https://github.com/camunda/camunda-bpm-platform/commit/365fdedd644f87752d1ad4e7b1d42a6b0997093c", "message": "SQUASH ME remove syso", "committedDate": "2020-03-30T15:42:53Z", "type": "commit"}, {"oid": "729c083bce0686a34c8e053fe2bcaa151e032c86", "url": "https://github.com/camunda/camunda-bpm-platform/commit/729c083bce0686a34c8e053fe2bcaa151e032c86", "message": "SQUASH ME 4->64", "committedDate": "2020-03-30T15:43:21Z", "type": "commit"}]}