{"pr_number": 1306, "pr_title": "HDDS-4051. Remove whitelist/blacklist terminology from Ozone", "pr_author": "vivekratnavel", "pr_createdAt": "2020-08-09T04:31:30Z", "pr_url": "https://github.com/apache/ozone/pull/1306", "timeline": [{"oid": "743209b1fb8e366cf3dbdccbcd55bd14ed9757f6", "url": "https://github.com/apache/ozone/commit/743209b1fb8e366cf3dbdccbcd55bd14ed9757f6", "message": "HDDS-4051. Remove whitelist/blacklist terminology from Ozone", "committedDate": "2020-08-09T04:27:29Z", "type": "commit"}, {"id": "MDI0OlB1bGxSZXF1ZXN0UmV2aWV3Q29tbWVudDQ2NzU0NTc1MQ==", "url": "https://github.com/apache/ozone/pull/1306#discussion_r467545751", "body": "```suggestion\r\n   * Ignore tasks that failed reprocess step more than threshold times.\r\n```", "bodyText": "Suggested change\n        \n          \n    \n\n        \n      \n    \n    \n      \n          \n            \n               * Blocklist tasks that failed reprocess step more than threshold times.\n          \n          \n            \n               * Ignore tasks that failed reprocess step more than threshold times.", "bodyHTML": "  <div class=\"my-2 border rounded-1 js-suggested-changes-blob diff-view js-check-bidi\" id=\"\">\n    <div class=\"f6 p-2 lh-condensed border-bottom d-flex\">\n      <div class=\"flex-auto flex-items-center color-fg-muted\">\n        Suggested change\n        <span class=\"tooltipped tooltipped-multiline tooltipped-s\" aria-label=\"This code change can be committed by users with write permissions.\">\n          <svg aria-hidden=\"true\" height=\"16\" viewBox=\"0 0 16 16\" version=\"1.1\" width=\"16\" data-view-component=\"true\" class=\"octicon octicon-info hide-sm\">\n    <path fill-rule=\"evenodd\" d=\"M8 1.5a6.5 6.5 0 100 13 6.5 6.5 0 000-13zM0 8a8 8 0 1116 0A8 8 0 010 8zm6.5-.25A.75.75 0 017.25 7h1a.75.75 0 01.75.75v2.75h.25a.75.75 0 010 1.5h-2a.75.75 0 010-1.5h.25v-2h-.25a.75.75 0 01-.75-.75zM8 6a1 1 0 100-2 1 1 0 000 2z\"></path>\n</svg>\n        </span>\n      </div>\n    </div>\n    <div itemprop=\"text\" class=\"blob-wrapper data file\" style=\"margin: 0; border: none; overflow-y: visible; overflow-x: auto;\">\n      <table class=\"d-table tab-size mb-0 width-full\" data-paste-markdown-skip=\"\">\n          <tbody><tr class=\"border-0\">\n            <td class=\"blob-num blob-num-deletion text-right border-0 px-2 py-1 lh-default\" data-line-number=\"\"></td>\n            <td class=\"border-0 px-2 py-1 blob-code-inner blob-code-deletion js-blob-code-deletion blob-code-marker-deletion\">   <span class=\"pl-k\">*</span> <span class=\"pl-smi x x-first x-last\">Blocklist</span> tasks that failed reprocess step more than threshold times.</td>\n          </tr>\n          <tr class=\"border-0\">\n            <td class=\"blob-num blob-num-addition text-right border-0 px-2 py-1 lh-default\" data-line-number=\"\"></td>\n            <td class=\"border-0 px-2 py-1 blob-code-inner blob-code-addition js-blob-code-addition blob-code-marker-addition\">   <span class=\"pl-k\">*</span> <span class=\"pl-smi x x-first x-last\">Ignore</span> tasks that failed reprocess step more than threshold times.</td>\n          </tr>\n      </tbody></table>\n    </div>\n    <div class=\"js-apply-changes\"></div>\n  </div>\n", "author": "adoroszlai", "createdAt": "2020-08-09T06:57:10Z", "path": "hadoop-ozone/recon/src/main/java/org/apache/hadoop/ozone/recon/tasks/ReconTaskControllerImpl.java", "diffHunk": "@@ -149,15 +149,15 @@ public synchronized void consumeOMEvents(OMUpdateEventBatch events,\n   }\n \n   /**\n-   * Blacklist tasks that failed reprocess step more than threshold times.\n+   * Blocklist tasks that failed reprocess step more than threshold times.", "originalCommit": "743209b1fb8e366cf3dbdccbcd55bd14ed9757f6", "replyToReviewId": null, "replies": null, "type": "inlineReview"}, {"id": "MDI0OlB1bGxSZXF1ZXN0UmV2aWV3Q29tbWVudDQ2NzU0NTc1Ng==", "url": "https://github.com/apache/ozone/pull/1306#discussion_r467545756", "body": "```suggestion\r\n  private void ignoreFailedTasks(List<String> failedTasks) {\r\n```", "bodyText": "Suggested change\n        \n          \n    \n\n        \n      \n    \n    \n      \n          \n            \n              private void blocklistFailedTasks(List<String> failedTasks) {\n          \n          \n            \n              private void ignoreFailedTasks(List<String> failedTasks) {", "bodyHTML": "  <div class=\"my-2 border rounded-1 js-suggested-changes-blob diff-view js-check-bidi\" id=\"\">\n    <div class=\"f6 p-2 lh-condensed border-bottom d-flex\">\n      <div class=\"flex-auto flex-items-center color-fg-muted\">\n        Suggested change\n        <span class=\"tooltipped tooltipped-multiline tooltipped-s\" aria-label=\"This code change can be committed by users with write permissions.\">\n          <svg aria-hidden=\"true\" height=\"16\" viewBox=\"0 0 16 16\" version=\"1.1\" width=\"16\" data-view-component=\"true\" class=\"octicon octicon-info hide-sm\">\n    <path fill-rule=\"evenodd\" d=\"M8 1.5a6.5 6.5 0 100 13 6.5 6.5 0 000-13zM0 8a8 8 0 1116 0A8 8 0 010 8zm6.5-.25A.75.75 0 017.25 7h1a.75.75 0 01.75.75v2.75h.25a.75.75 0 010 1.5h-2a.75.75 0 010-1.5h.25v-2h-.25a.75.75 0 01-.75-.75zM8 6a1 1 0 100-2 1 1 0 000 2z\"></path>\n</svg>\n        </span>\n      </div>\n    </div>\n    <div itemprop=\"text\" class=\"blob-wrapper data file\" style=\"margin: 0; border: none; overflow-y: visible; overflow-x: auto;\">\n      <table class=\"d-table tab-size mb-0 width-full\" data-paste-markdown-skip=\"\">\n          <tbody><tr class=\"border-0\">\n            <td class=\"blob-num blob-num-deletion text-right border-0 px-2 py-1 lh-default\" data-line-number=\"\"></td>\n            <td class=\"border-0 px-2 py-1 blob-code-inner blob-code-deletion js-blob-code-deletion blob-code-marker-deletion\">  <span class=\"pl-k\">private</span> <span class=\"pl-k\">void</span> <span class=\"x x-first x-last\">blocklistFailedTasks</span>(<span class=\"pl-k\">List&lt;<span class=\"pl-smi\">String</span>&gt;</span> failedTasks) {</td>\n          </tr>\n          <tr class=\"border-0\">\n            <td class=\"blob-num blob-num-addition text-right border-0 px-2 py-1 lh-default\" data-line-number=\"\"></td>\n            <td class=\"border-0 px-2 py-1 blob-code-inner blob-code-addition js-blob-code-addition blob-code-marker-addition\">  <span class=\"pl-k\">private</span> <span class=\"pl-k\">void</span> <span class=\"x x-first x-last\">ignoreFailedTasks</span>(<span class=\"pl-k\">List&lt;<span class=\"pl-smi\">String</span>&gt;</span> failedTasks) {</td>\n          </tr>\n      </tbody></table>\n    </div>\n    <div class=\"js-apply-changes\"></div>\n  </div>\n", "author": "adoroszlai", "createdAt": "2020-08-09T06:57:21Z", "path": "hadoop-ozone/recon/src/main/java/org/apache/hadoop/ozone/recon/tasks/ReconTaskControllerImpl.java", "diffHunk": "@@ -149,15 +149,15 @@ public synchronized void consumeOMEvents(OMUpdateEventBatch events,\n   }\n \n   /**\n-   * Blacklist tasks that failed reprocess step more than threshold times.\n+   * Blocklist tasks that failed reprocess step more than threshold times.\n    * @param failedTasks list of failed tasks.\n    */\n-  private void blacklistFailedTasks(List<String> failedTasks) {\n+  private void blocklistFailedTasks(List<String> failedTasks) {", "originalCommit": "743209b1fb8e366cf3dbdccbcd55bd14ed9757f6", "replyToReviewId": null, "replies": null, "type": "inlineReview"}, {"id": "MDI0OlB1bGxSZXF1ZXN0UmV2aWV3Q29tbWVudDQ2NzU0NTc4Mg==", "url": "https://github.com/apache/ozone/pull/1306#discussion_r467545782", "body": "```suggestion\r\n        LOG.info(\"Ignoring task since it failed retry and \" +\r\n```", "bodyText": "Suggested change\n        \n          \n    \n\n        \n      \n    \n    \n      \n          \n            \n                    LOG.info(\"Blocklisting Task since it failed retry and \" +\n          \n          \n            \n                    LOG.info(\"Ignoring task since it failed retry and \" +", "bodyHTML": "  <div class=\"my-2 border rounded-1 js-suggested-changes-blob diff-view js-check-bidi\" id=\"\">\n    <div class=\"f6 p-2 lh-condensed border-bottom d-flex\">\n      <div class=\"flex-auto flex-items-center color-fg-muted\">\n        Suggested change\n        <span class=\"tooltipped tooltipped-multiline tooltipped-s\" aria-label=\"This code change can be committed by users with write permissions.\">\n          <svg aria-hidden=\"true\" height=\"16\" viewBox=\"0 0 16 16\" version=\"1.1\" width=\"16\" data-view-component=\"true\" class=\"octicon octicon-info hide-sm\">\n    <path fill-rule=\"evenodd\" d=\"M8 1.5a6.5 6.5 0 100 13 6.5 6.5 0 000-13zM0 8a8 8 0 1116 0A8 8 0 010 8zm6.5-.25A.75.75 0 017.25 7h1a.75.75 0 01.75.75v2.75h.25a.75.75 0 010 1.5h-2a.75.75 0 010-1.5h.25v-2h-.25a.75.75 0 01-.75-.75zM8 6a1 1 0 100-2 1 1 0 000 2z\"></path>\n</svg>\n        </span>\n      </div>\n    </div>\n    <div itemprop=\"text\" class=\"blob-wrapper data file\" style=\"margin: 0; border: none; overflow-y: visible; overflow-x: auto;\">\n      <table class=\"d-table tab-size mb-0 width-full\" data-paste-markdown-skip=\"\">\n          <tbody><tr class=\"border-0\">\n            <td class=\"blob-num blob-num-deletion text-right border-0 px-2 py-1 lh-default\" data-line-number=\"\"></td>\n            <td class=\"border-0 px-2 py-1 blob-code-inner blob-code-deletion js-blob-code-deletion blob-code-marker-deletion\">        <span class=\"pl-c1\">LOG</span><span class=\"pl-k\">.</span>info(<span class=\"pl-s\"><span class=\"pl-pds\">\"</span><span class=\"x x-first x-last\">Blocklisting Task</span> since it failed retry and <span class=\"pl-pds\">\"</span></span> <span class=\"pl-k\">+</span></td>\n          </tr>\n          <tr class=\"border-0\">\n            <td class=\"blob-num blob-num-addition text-right border-0 px-2 py-1 lh-default\" data-line-number=\"\"></td>\n            <td class=\"border-0 px-2 py-1 blob-code-inner blob-code-addition js-blob-code-addition blob-code-marker-addition\">        <span class=\"pl-c1\">LOG</span><span class=\"pl-k\">.</span>info(<span class=\"pl-s\"><span class=\"pl-pds\">\"</span><span class=\"x x-first x-last\">Ignoring task</span> since it failed retry and <span class=\"pl-pds\">\"</span></span> <span class=\"pl-k\">+</span></td>\n          </tr>\n      </tbody></table>\n    </div>\n    <div class=\"js-apply-changes\"></div>\n  </div>\n", "author": "adoroszlai", "createdAt": "2020-08-09T06:57:41Z", "path": "hadoop-ozone/recon/src/main/java/org/apache/hadoop/ozone/recon/tasks/ReconTaskControllerImpl.java", "diffHunk": "@@ -149,15 +149,15 @@ public synchronized void consumeOMEvents(OMUpdateEventBatch events,\n   }\n \n   /**\n-   * Blacklist tasks that failed reprocess step more than threshold times.\n+   * Blocklist tasks that failed reprocess step more than threshold times.\n    * @param failedTasks list of failed tasks.\n    */\n-  private void blacklistFailedTasks(List<String> failedTasks) {\n+  private void blocklistFailedTasks(List<String> failedTasks) {\n     for (String taskName : failedTasks) {\n       LOG.info(\"Reprocess step failed for task {}.\", taskName);\n       if (taskFailureCounter.get(taskName).incrementAndGet() >\n           TASK_FAILURE_THRESHOLD) {\n-        LOG.info(\"Blacklisting Task since it failed retry and \" +\n+        LOG.info(\"Blocklisting Task since it failed retry and \" +", "originalCommit": "743209b1fb8e366cf3dbdccbcd55bd14ed9757f6", "replyToReviewId": null, "replies": null, "type": "inlineReview"}, {"id": "MDI0OlB1bGxSZXF1ZXN0UmV2aWV3Q29tbWVudDQ2NzU0NTgwOQ==", "url": "https://github.com/apache/ozone/pull/1306#discussion_r467545809", "body": "```suggestion\r\n  public void testBadBehavedTaskIsIgnored() throws Exception {\r\n```", "bodyText": "Suggested change\n        \n          \n    \n\n        \n      \n    \n    \n      \n          \n            \n              public void testBadBehavedTaskBlocklisting() throws Exception {\n          \n          \n            \n              public void testBadBehavedTaskIsIgnored() throws Exception {", "bodyHTML": "  <div class=\"my-2 border rounded-1 js-suggested-changes-blob diff-view js-check-bidi\" id=\"\">\n    <div class=\"f6 p-2 lh-condensed border-bottom d-flex\">\n      <div class=\"flex-auto flex-items-center color-fg-muted\">\n        Suggested change\n        <span class=\"tooltipped tooltipped-multiline tooltipped-s\" aria-label=\"This code change can be committed by users with write permissions.\">\n          <svg aria-hidden=\"true\" height=\"16\" viewBox=\"0 0 16 16\" version=\"1.1\" width=\"16\" data-view-component=\"true\" class=\"octicon octicon-info hide-sm\">\n    <path fill-rule=\"evenodd\" d=\"M8 1.5a6.5 6.5 0 100 13 6.5 6.5 0 000-13zM0 8a8 8 0 1116 0A8 8 0 010 8zm6.5-.25A.75.75 0 017.25 7h1a.75.75 0 01.75.75v2.75h.25a.75.75 0 010 1.5h-2a.75.75 0 010-1.5h.25v-2h-.25a.75.75 0 01-.75-.75zM8 6a1 1 0 100-2 1 1 0 000 2z\"></path>\n</svg>\n        </span>\n      </div>\n    </div>\n    <div itemprop=\"text\" class=\"blob-wrapper data file\" style=\"margin: 0; border: none; overflow-y: visible; overflow-x: auto;\">\n      <table class=\"d-table tab-size mb-0 width-full\" data-paste-markdown-skip=\"\">\n          <tbody><tr class=\"border-0\">\n            <td class=\"blob-num blob-num-deletion text-right border-0 px-2 py-1 lh-default\" data-line-number=\"\"></td>\n            <td class=\"border-0 px-2 py-1 blob-code-inner blob-code-deletion js-blob-code-deletion blob-code-marker-deletion\">  <span class=\"pl-k\">public</span> <span class=\"pl-k\">void</span> <span class=\"x x-first x-last\">testBadBehavedTaskBlocklisting</span>() throws <span class=\"pl-smi\">Exception</span> {</td>\n          </tr>\n          <tr class=\"border-0\">\n            <td class=\"blob-num blob-num-addition text-right border-0 px-2 py-1 lh-default\" data-line-number=\"\"></td>\n            <td class=\"border-0 px-2 py-1 blob-code-inner blob-code-addition js-blob-code-addition blob-code-marker-addition\">  <span class=\"pl-k\">public</span> <span class=\"pl-k\">void</span> <span class=\"x x-first x-last\">testBadBehavedTaskIsIgnored</span>() throws <span class=\"pl-smi\">Exception</span> {</td>\n          </tr>\n      </tbody></table>\n    </div>\n    <div class=\"js-apply-changes\"></div>\n  </div>\n", "author": "adoroszlai", "createdAt": "2020-08-09T06:58:02Z", "path": "hadoop-ozone/recon/src/test/java/org/apache/hadoop/ozone/recon/tasks/TestReconTaskControllerImpl.java", "diffHunk": "@@ -131,7 +131,7 @@ public void testFailedTaskRetryLogic() throws Exception {\n   }\n \n   @Test\n-  public void testBadBehavedTaskBlacklisting() throws Exception {\n+  public void testBadBehavedTaskBlocklisting() throws Exception {", "originalCommit": "743209b1fb8e366cf3dbdccbcd55bd14ed9757f6", "replyToReviewId": null, "replies": null, "type": "inlineReview"}, {"id": "MDI0OlB1bGxSZXF1ZXN0UmV2aWV3Q29tbWVudDQ2NzU0NTgxNA==", "url": "https://github.com/apache/ozone/pull/1306#discussion_r467545814", "body": "```suggestion\r\n    //Should be ignored now.\r\n```", "bodyText": "Suggested change\n        \n          \n    \n\n        \n      \n    \n    \n      \n          \n            \n                //Should be blocklisted now.\n          \n          \n            \n                //Should be ignored now.", "bodyHTML": "  <div class=\"my-2 border rounded-1 js-suggested-changes-blob diff-view js-check-bidi\" id=\"\">\n    <div class=\"f6 p-2 lh-condensed border-bottom d-flex\">\n      <div class=\"flex-auto flex-items-center color-fg-muted\">\n        Suggested change\n        <span class=\"tooltipped tooltipped-multiline tooltipped-s\" aria-label=\"This code change can be committed by users with write permissions.\">\n          <svg aria-hidden=\"true\" height=\"16\" viewBox=\"0 0 16 16\" version=\"1.1\" width=\"16\" data-view-component=\"true\" class=\"octicon octicon-info hide-sm\">\n    <path fill-rule=\"evenodd\" d=\"M8 1.5a6.5 6.5 0 100 13 6.5 6.5 0 000-13zM0 8a8 8 0 1116 0A8 8 0 010 8zm6.5-.25A.75.75 0 017.25 7h1a.75.75 0 01.75.75v2.75h.25a.75.75 0 010 1.5h-2a.75.75 0 010-1.5h.25v-2h-.25a.75.75 0 01-.75-.75zM8 6a1 1 0 100-2 1 1 0 000 2z\"></path>\n</svg>\n        </span>\n      </div>\n    </div>\n    <div itemprop=\"text\" class=\"blob-wrapper data file\" style=\"margin: 0; border: none; overflow-y: visible; overflow-x: auto;\">\n      <table class=\"d-table tab-size mb-0 width-full\" data-paste-markdown-skip=\"\">\n          <tbody><tr class=\"border-0\">\n            <td class=\"blob-num blob-num-deletion text-right border-0 px-2 py-1 lh-default\" data-line-number=\"\"></td>\n            <td class=\"border-0 px-2 py-1 blob-code-inner blob-code-deletion js-blob-code-deletion blob-code-marker-deletion\">    <span class=\"pl-c\"><span class=\"pl-c\">//</span>Should be <span class=\"x x-first x-last\">blocklisted</span> now.</span></td>\n          </tr>\n          <tr class=\"border-0\">\n            <td class=\"blob-num blob-num-addition text-right border-0 px-2 py-1 lh-default\" data-line-number=\"\"></td>\n            <td class=\"border-0 px-2 py-1 blob-code-inner blob-code-addition js-blob-code-addition blob-code-marker-addition\">    <span class=\"pl-c\"><span class=\"pl-c\">//</span>Should be <span class=\"x x-first x-last\">ignored</span> now.</span></td>\n          </tr>\n      </tbody></table>\n    </div>\n    <div class=\"js-apply-changes\"></div>\n  </div>\n", "author": "adoroszlai", "createdAt": "2020-08-09T06:58:08Z", "path": "hadoop-ozone/recon/src/test/java/org/apache/hadoop/ozone/recon/tasks/TestReconTaskControllerImpl.java", "diffHunk": "@@ -151,7 +151,7 @@ public void testBadBehavedTaskBlacklisting() throws Exception {\n           .get(dummyReconDBTask.getTaskName()));\n     }\n \n-    //Should be blacklisted now.\n+    //Should be blocklisted now.", "originalCommit": "743209b1fb8e366cf3dbdccbcd55bd14ed9757f6", "replyToReviewId": null, "replies": null, "type": "inlineReview"}, {"id": "MDI0OlB1bGxSZXF1ZXN0UmV2aWV3Q29tbWVudDQ2NzU0NTg1OA==", "url": "https://github.com/apache/ozone/pull/1306#discussion_r467545858", "body": "```suggestion\r\n          ignoreFailedTasks(reprocessFailedTasks);\r\n```", "bodyText": "Suggested change\n        \n          \n    \n\n        \n      \n    \n    \n      \n          \n            \n                      blocklistFailedTasks(reprocessFailedTasks);\n          \n          \n            \n                      ignoreFailedTasks(reprocessFailedTasks);", "bodyHTML": "  <div class=\"my-2 border rounded-1 js-suggested-changes-blob diff-view js-check-bidi\" id=\"\">\n    <div class=\"f6 p-2 lh-condensed border-bottom d-flex\">\n      <div class=\"flex-auto flex-items-center color-fg-muted\">\n        Suggested change\n        <span class=\"tooltipped tooltipped-multiline tooltipped-s\" aria-label=\"This code change can be committed by users with write permissions.\">\n          <svg aria-hidden=\"true\" height=\"16\" viewBox=\"0 0 16 16\" version=\"1.1\" width=\"16\" data-view-component=\"true\" class=\"octicon octicon-info hide-sm\">\n    <path fill-rule=\"evenodd\" d=\"M8 1.5a6.5 6.5 0 100 13 6.5 6.5 0 000-13zM0 8a8 8 0 1116 0A8 8 0 010 8zm6.5-.25A.75.75 0 017.25 7h1a.75.75 0 01.75.75v2.75h.25a.75.75 0 010 1.5h-2a.75.75 0 010-1.5h.25v-2h-.25a.75.75 0 01-.75-.75zM8 6a1 1 0 100-2 1 1 0 000 2z\"></path>\n</svg>\n        </span>\n      </div>\n    </div>\n    <div itemprop=\"text\" class=\"blob-wrapper data file\" style=\"margin: 0; border: none; overflow-y: visible; overflow-x: auto;\">\n      <table class=\"d-table tab-size mb-0 width-full\" data-paste-markdown-skip=\"\">\n          <tbody><tr class=\"border-0\">\n            <td class=\"blob-num blob-num-deletion text-right border-0 px-2 py-1 lh-default\" data-line-number=\"\"></td>\n            <td class=\"border-0 px-2 py-1 blob-code-inner blob-code-deletion js-blob-code-deletion blob-code-marker-deletion\">          <span class=\"x x-first x-last\">blocklistFailedTasks</span>(reprocessFailedTasks);</td>\n          </tr>\n          <tr class=\"border-0\">\n            <td class=\"blob-num blob-num-addition text-right border-0 px-2 py-1 lh-default\" data-line-number=\"\"></td>\n            <td class=\"border-0 px-2 py-1 blob-code-inner blob-code-addition js-blob-code-addition blob-code-marker-addition\">          <span class=\"x x-first x-last\">ignoreFailedTasks</span>(reprocessFailedTasks);</td>\n          </tr>\n      </tbody></table>\n    </div>\n    <div class=\"js-apply-changes\"></div>\n  </div>\n", "author": "adoroszlai", "createdAt": "2020-08-09T06:58:40Z", "path": "hadoop-ozone/recon/src/main/java/org/apache/hadoop/ozone/recon/tasks/ReconTaskControllerImpl.java", "diffHunk": "@@ -140,7 +140,7 @@ public synchronized void consumeOMEvents(OMUpdateEventBatch events,\n           results = executorService.invokeAll(tasks);\n           List<String> reprocessFailedTasks =\n               processTaskResults(results, events);\n-          blacklistFailedTasks(reprocessFailedTasks);\n+          blocklistFailedTasks(reprocessFailedTasks);", "originalCommit": "743209b1fb8e366cf3dbdccbcd55bd14ed9757f6", "replyToReviewId": null, "replies": null, "type": "inlineReview"}, {"id": "MDI0OlB1bGxSZXF1ZXN0UmV2aWV3Q29tbWVudDQ2NzU0NTg4Ng==", "url": "https://github.com/apache/ozone/pull/1306#discussion_r467545886", "body": "```suggestion\r\n   * (ignored).\r\n```", "bodyText": "Suggested change\n        \n          \n    \n\n        \n      \n    \n    \n      \n          \n            \n               * (blocklisted).\n          \n          \n            \n               * (ignored).", "bodyHTML": "  <div class=\"my-2 border rounded-1 js-suggested-changes-blob diff-view js-check-bidi\" id=\"\">\n    <div class=\"f6 p-2 lh-condensed border-bottom d-flex\">\n      <div class=\"flex-auto flex-items-center color-fg-muted\">\n        Suggested change\n        <span class=\"tooltipped tooltipped-multiline tooltipped-s\" aria-label=\"This code change can be committed by users with write permissions.\">\n          <svg aria-hidden=\"true\" height=\"16\" viewBox=\"0 0 16 16\" version=\"1.1\" width=\"16\" data-view-component=\"true\" class=\"octicon octicon-info hide-sm\">\n    <path fill-rule=\"evenodd\" d=\"M8 1.5a6.5 6.5 0 100 13 6.5 6.5 0 000-13zM0 8a8 8 0 1116 0A8 8 0 010 8zm6.5-.25A.75.75 0 017.25 7h1a.75.75 0 01.75.75v2.75h.25a.75.75 0 010 1.5h-2a.75.75 0 010-1.5h.25v-2h-.25a.75.75 0 01-.75-.75zM8 6a1 1 0 100-2 1 1 0 000 2z\"></path>\n</svg>\n        </span>\n      </div>\n    </div>\n    <div itemprop=\"text\" class=\"blob-wrapper data file\" style=\"margin: 0; border: none; overflow-y: visible; overflow-x: auto;\">\n      <table class=\"d-table tab-size mb-0 width-full\" data-paste-markdown-skip=\"\">\n          <tbody><tr class=\"border-0\">\n            <td class=\"blob-num blob-num-deletion text-right border-0 px-2 py-1 lh-default\" data-line-number=\"\"></td>\n            <td class=\"border-0 px-2 py-1 blob-code-inner blob-code-deletion js-blob-code-deletion blob-code-marker-deletion\">   <span class=\"pl-k\">*</span> (<span class=\"x x-first x-last\">blocklisted</span>)<span class=\"pl-c1\">.</span></td>\n          </tr>\n          <tr class=\"border-0\">\n            <td class=\"blob-num blob-num-addition text-right border-0 px-2 py-1 lh-default\" data-line-number=\"\"></td>\n            <td class=\"border-0 px-2 py-1 blob-code-inner blob-code-addition js-blob-code-addition blob-code-marker-addition\">   <span class=\"pl-k\">*</span> (<span class=\"x x-first x-last\">ignored</span>)<span class=\"pl-c1\">.</span></td>\n          </tr>\n      </tbody></table>\n    </div>\n    <div class=\"js-apply-changes\"></div>\n  </div>\n", "author": "adoroszlai", "createdAt": "2020-08-09T06:59:06Z", "path": "hadoop-ozone/recon/src/main/java/org/apache/hadoop/ozone/recon/tasks/ReconTaskControllerImpl.java", "diffHunk": "@@ -94,7 +94,7 @@ public void registerTask(ReconOmTask task) {\n    * For every registered task, we try process step twice and then reprocess\n    * once (if process failed twice) to absorb the events. If a task has failed\n    * reprocess call more than 2 times across events, it is unregistered\n-   * (blacklisted).\n+   * (blocklisted).", "originalCommit": "743209b1fb8e366cf3dbdccbcd55bd14ed9757f6", "replyToReviewId": null, "replies": null, "type": "inlineReview"}, {"oid": "bc00022548a5977a63e04575e313018f7e9b757a", "url": "https://github.com/apache/ozone/commit/bc00022548a5977a63e04575e313018f7e9b757a", "message": "Apply suggestions from code review\n\nCo-authored-by: Doroszlai, Attila <6454655+adoroszlai@users.noreply.github.com>", "committedDate": "2020-08-09T19:27:53Z", "type": "commit"}]}