{"pr_number": 8465, "pr_title": "MINOR: Fix grammar error message for InvalidRecordException", "pr_author": "tuvtran", "pr_createdAt": "2020-04-11T03:24:56Z", "pr_url": "https://github.com/apache/kafka/pull/8465", "timeline": [{"oid": "3e1103872e33a57f0fb8c424f08f0aac98bbf314", "url": "https://github.com/apache/kafka/commit/3e1103872e33a57f0fb8c424f08f0aac98bbf314", "message": "Fix error message for InvalidRecordException", "committedDate": "2020-04-11T03:03:41Z", "type": "commit"}, {"id": "MDI0OlB1bGxSZXF1ZXN0UmV2aWV3Q29tbWVudDQwNzc0NjI4NA==", "url": "https://github.com/apache/kafka/pull/8465#discussion_r407746284", "body": "```suggestion\r\n    INVALID_RECORD(87, \"This record has failed the validation on broker and hence will be rejected.\", InvalidRecordException::new),\r\n```", "bodyText": "Suggested change\n        \n          \n    \n\n        \n      \n    \n    \n      \n          \n            \n                INVALID_RECORD(87, \"This record has failed the validation on broker and will hence be rejected.\", InvalidRecordException::new),\n          \n          \n            \n                INVALID_RECORD(87, \"This record has failed the validation on broker and hence will be rejected.\", InvalidRecordException::new),", "bodyHTML": "  <div class=\"my-2 border rounded-1 js-suggested-changes-blob diff-view js-check-bidi\" id=\"\">\n    <div class=\"f6 p-2 lh-condensed border-bottom d-flex\">\n      <div class=\"flex-auto flex-items-center color-fg-muted\">\n        Suggested change\n        <span class=\"tooltipped tooltipped-multiline tooltipped-s\" aria-label=\"This code change can be committed by users with write permissions.\">\n          <svg aria-hidden=\"true\" height=\"16\" viewBox=\"0 0 16 16\" version=\"1.1\" width=\"16\" data-view-component=\"true\" class=\"octicon octicon-info hide-sm\">\n    <path fill-rule=\"evenodd\" d=\"M8 1.5a6.5 6.5 0 100 13 6.5 6.5 0 000-13zM0 8a8 8 0 1116 0A8 8 0 010 8zm6.5-.25A.75.75 0 017.25 7h1a.75.75 0 01.75.75v2.75h.25a.75.75 0 010 1.5h-2a.75.75 0 010-1.5h.25v-2h-.25a.75.75 0 01-.75-.75zM8 6a1 1 0 100-2 1 1 0 000 2z\"></path>\n</svg>\n        </span>\n      </div>\n    </div>\n    <div itemprop=\"text\" class=\"blob-wrapper data file\" style=\"margin: 0; border: none; overflow-y: visible; overflow-x: auto;\">\n      <table class=\"d-table tab-size mb-0 width-full\" data-paste-markdown-skip=\"\">\n          <tbody><tr class=\"border-0\">\n            <td class=\"blob-num blob-num-deletion text-right border-0 px-2 py-1 lh-default\" data-line-number=\"\"></td>\n            <td class=\"border-0 px-2 py-1 blob-code-inner blob-code-deletion js-blob-code-deletion blob-code-marker-deletion\">    <span class=\"pl-c1\">INVALID_RECORD</span>(<span class=\"pl-c1\">87</span>, <span class=\"pl-s\"><span class=\"pl-pds\">\"</span>This record has failed the validation on broker and <span class=\"x x-first x-last\">will </span>hence be rejected.<span class=\"pl-pds\">\"</span></span>, <span class=\"pl-smi\">InvalidRecordException</span><span class=\"pl-k\">::</span><span class=\"pl-k\">new</span>),</td>\n          </tr>\n          <tr class=\"border-0\">\n            <td class=\"blob-num blob-num-addition text-right border-0 px-2 py-1 lh-default\" data-line-number=\"\"></td>\n            <td class=\"border-0 px-2 py-1 blob-code-inner blob-code-addition js-blob-code-addition blob-code-marker-addition\">    <span class=\"pl-c1\">INVALID_RECORD</span>(<span class=\"pl-c1\">87</span>, <span class=\"pl-s\"><span class=\"pl-pds\">\"</span>This record has failed the validation on broker and hence<span class=\"x x-first x-last\"> will</span> be rejected.<span class=\"pl-pds\">\"</span></span>, <span class=\"pl-smi\">InvalidRecordException</span><span class=\"pl-k\">::</span><span class=\"pl-k\">new</span>),</td>\n          </tr>\n      </tbody></table>\n    </div>\n    <div class=\"js-apply-changes\"></div>\n  </div>\n", "author": "kkonstantine", "createdAt": "2020-04-13T22:00:19Z", "path": "clients/src/main/java/org/apache/kafka/common/protocol/Errors.java", "diffHunk": "@@ -318,7 +318,7 @@\n             NoReassignmentInProgressException::new),\n     GROUP_SUBSCRIBED_TO_TOPIC(86, \"Deleting offsets of a topic is forbidden while the consumer group is actively subscribed to it.\",\n         GroupSubscribedToTopicException::new),\n-    INVALID_RECORD(87, \"This record has failed the validation on broker and hence be rejected.\", InvalidRecordException::new),\n+    INVALID_RECORD(87, \"This record has failed the validation on broker and will hence be rejected.\", InvalidRecordException::new),", "originalCommit": "3e1103872e33a57f0fb8c424f08f0aac98bbf314", "replyToReviewId": null, "replies": null, "type": "inlineReview"}, {"oid": "df7bc72ab159bc085cb03aa92828d1a27c823d7e", "url": "https://github.com/apache/kafka/commit/df7bc72ab159bc085cb03aa92828d1a27c823d7e", "message": "Update clients/src/main/java/org/apache/kafka/common/protocol/Errors.java\n\nCo-Authored-By: Konstantine Karantasis <konstantine@confluent.io>", "committedDate": "2020-04-16T21:14:48Z", "type": "commit"}]}