{"pr_number": 8771, "pr_title": "SAK-44550 Message bundle manager throws error", "pr_author": "bgarciaentornos", "pr_createdAt": "2020-11-03T13:22:56Z", "pr_url": "https://github.com/sakaiproject/sakai/pull/8771", "timeline": [{"oid": "9ebd980233186c1d5795e5aa801da7e18ffdc97a", "url": "https://github.com/sakaiproject/sakai/commit/9ebd980233186c1d5795e5aa801da7e18ffdc97a", "message": "SAK-44550 Message bundle manager throws error", "committedDate": "2020-11-03T13:22:12Z", "type": "commit"}, {"id": "MDI0OlB1bGxSZXF1ZXN0UmV2aWV3Q29tbWVudDUxNjcxMzAyMg==", "url": "https://github.com/sakaiproject/sakai/pull/8771#discussion_r516713022", "body": "```suggestion\r\n            if (pageSize >= 0) {\r\n                query.setMaxResults(pageSize);\r\n            }\r\n```", "bodyText": "Suggested change\n        \n          \n    \n\n        \n      \n    \n    \n      \n          \n            \n                        if(pageSize >= 0) {\n          \n          \n            \n                            query.setMaxResults(pageSize);\n          \n          \n            \n                        }\n          \n          \n            \n                        if (pageSize >= 0) {\n          \n          \n            \n                            query.setMaxResults(pageSize);\n          \n          \n            \n                        }", "bodyHTML": "  <div class=\"my-2 border rounded-1 js-suggested-changes-blob diff-view js-check-bidi\" id=\"\">\n    <div class=\"f6 p-2 lh-condensed border-bottom d-flex\">\n      <div class=\"flex-auto flex-items-center color-fg-muted\">\n        Suggested change\n        <span class=\"tooltipped tooltipped-multiline tooltipped-s\" aria-label=\"This code change can be committed by users with write permissions.\">\n          <svg aria-hidden=\"true\" height=\"16\" viewBox=\"0 0 16 16\" version=\"1.1\" width=\"16\" data-view-component=\"true\" class=\"octicon octicon-info hide-sm\">\n    <path fill-rule=\"evenodd\" d=\"M8 1.5a6.5 6.5 0 100 13 6.5 6.5 0 000-13zM0 8a8 8 0 1116 0A8 8 0 010 8zm6.5-.25A.75.75 0 017.25 7h1a.75.75 0 01.75.75v2.75h.25a.75.75 0 010 1.5h-2a.75.75 0 010-1.5h.25v-2h-.25a.75.75 0 01-.75-.75zM8 6a1 1 0 100-2 1 1 0 000 2z\"></path>\n</svg>\n        </span>\n      </div>\n    </div>\n    <div itemprop=\"text\" class=\"blob-wrapper data file\" style=\"margin: 0; border: none; overflow-y: visible; overflow-x: auto;\">\n      <table class=\"d-table tab-size mb-0 width-full\" data-paste-markdown-skip=\"\">\n          <tbody><tr class=\"border-0\">\n            <td class=\"blob-num blob-num-deletion text-right border-0 px-2 py-1 lh-default\" data-line-number=\"471\"></td>\n            <td class=\"border-0 px-2 py-1 blob-code-inner blob-code-deletion js-blob-code-deletion blob-code-marker-deletion\">            <span class=\"pl-k\">if</span>(pageSize <span class=\"pl-k\">&gt;=</span> <span class=\"pl-c1\">0</span>) {</td>\n          </tr>\n          <tr class=\"border-0\">\n            <td class=\"blob-num blob-num-deletion text-right border-0 px-2 py-1 lh-default\" data-line-number=\"472\"></td>\n            <td class=\"border-0 px-2 py-1 blob-code-inner blob-code-deletion js-blob-code-deletion blob-code-marker-deletion\">                query<span class=\"pl-k\">.</span>setMaxResults(pageSize);</td>\n          </tr>\n          <tr class=\"border-0\">\n            <td class=\"blob-num blob-num-deletion text-right border-0 px-2 py-1 lh-default\" data-line-number=\"473\"></td>\n            <td class=\"border-0 px-2 py-1 blob-code-inner blob-code-deletion js-blob-code-deletion blob-code-marker-deletion\">            }</td>\n          </tr>\n          <tr class=\"border-0\">\n            <td class=\"blob-num blob-num-addition text-right border-0 px-2 py-1 lh-default\" data-line-number=\"471\"></td>\n            <td class=\"border-0 px-2 py-1 blob-code-inner blob-code-addition js-blob-code-addition blob-code-marker-addition\">            <span class=\"pl-k\">if</span><span class=\"x x-first x-last\"> </span>(pageSize <span class=\"pl-k\">&gt;=</span> <span class=\"pl-c1\">0</span>) {</td>\n          </tr>\n          <tr class=\"border-0\">\n            <td class=\"blob-num blob-num-addition text-right border-0 px-2 py-1 lh-default\" data-line-number=\"472\"></td>\n            <td class=\"border-0 px-2 py-1 blob-code-inner blob-code-addition js-blob-code-addition blob-code-marker-addition\">                query<span class=\"pl-k\">.</span>setMaxResults(pageSize);</td>\n          </tr>\n          <tr class=\"border-0\">\n            <td class=\"blob-num blob-num-addition text-right border-0 px-2 py-1 lh-default\" data-line-number=\"473\"></td>\n            <td class=\"border-0 px-2 py-1 blob-code-inner blob-code-addition js-blob-code-addition blob-code-marker-addition\">            }</td>\n          </tr>\n      </tbody></table>\n    </div>\n    <div class=\"js-apply-changes\"></div>\n  </div>\n", "author": "ern", "createdAt": "2020-11-03T14:36:21Z", "path": "kernel/kernel-impl/src/main/java/org/sakaiproject/messagebundle/impl/MessageBundleServiceImpl.java", "diffHunk": "@@ -466,7 +466,9 @@ protected int executeCountQuery(String query) {\n         try {\n             query = sessionFactory.getCurrentSession().createQuery(queryString);\n             query.setFirstResult(startingIndex);\n-            query.setMaxResults(pageSize);\n+            if(pageSize >= 0) {\n+                query.setMaxResults(pageSize);\n+            }", "originalCommit": "9ebd980233186c1d5795e5aa801da7e18ffdc97a", "replyToReviewId": null, "replies": null, "type": "inlineReview"}, {"oid": "957270f0be8de03492f3276a391419651b01550f", "url": "https://github.com/sakaiproject/sakai/commit/957270f0be8de03492f3276a391419651b01550f", "message": "fix spacing", "committedDate": "2020-11-03T14:36:46Z", "type": "commit"}]}